_pytest-stubs/__init__.pyi
_pytest-stubs/_code.pyi
_pytest-stubs/capture.pyi
_pytest-stubs/config.pyi
_pytest-stubs/fixtures.pyi
_pytest-stubs/logging.pyi
_pytest-stubs/monkeypatch.pyi
bokeh-stubs/__init__.pyi
bokeh-stubs/layouts.pyi
bokeh-stubs/models.pyi
bokeh-stubs/palettes.pyi
bokeh-stubs/plotting.pyi
bokeh-stubs/application/__init__.pyi
bokeh-stubs/application/handlers.pyi
bokeh-stubs/command/__init__.pyi
bokeh-stubs/command/util.pyi
bokeh-stubs/server/__init__.pyi
bokeh-stubs/server/contexts.pyi
bokeh-stubs/server/server.pyi
colorlog-stubs/__init__.pyi
dateparser-stubs/__init__.pyi
elasticsearch-stubs/__init__.pyi
elasticsearch-stubs/exceptions.pyi
elasticsearch-stubs/helpers.pyi
elasticsearch_dsl-stubs/__init__.pyi
lxml-stubs/__init__.pyi
lxml-stubs/etree.pyi
lxml-stubs/html.pyi
nasty_typeshed/__init__.py
nasty_typeshed/_version.py
nox-stubs/__init__.pyi
nox-stubs/sessions.pyi
overrides-stubs/__init__.pyi
pytest-stubs/__init__.pyi
responses-stubs/__init__.pyi
setuptools-stubs/__init__.pyi
somajo-stubs/__init__.pyi
stopwordsiso-stubs/__init__.pyi
tqdm-stubs/__init__.pyi
tweepy-stubs/__init__.pyi
typing_inspect-stubs/__init__.pyi
urllib3-stubs/__init__.pyi
zstandard-stubs/__init__.pyi
nasty_typeshed-0.1.0.dist-info/LICENSE
nasty_typeshed-0.1.0.dist-info/METADATA
nasty_typeshed-0.1.0.dist-info/WHEEL
nasty_typeshed-0.1.0.dist-info/top_level.txt
nasty_typeshed-0.1.0.dist-info/zip-safe
nasty_typeshed-0.1.0.dist-info/RECORD
